actchainkit/__init__.py
actchainkit/ccxt_orderbook_loop.py
actchainkit/exceptions.py
actchainkit/periodic_loops.py
actchainkit-0.1.2.dist-info/METADATA
actchainkit-0.1.2.dist-info/WHEEL
actchainkit-0.1.2.dist-info/RECORD
